creditkit_tools/__init__.py
creditkit_tools/auxiliar_message.py
creditkit_tools/format_text.py
creditkit_tools/measure_time.py
creditkit_tools-0.0.4.dist-info/LICENSE
creditkit_tools-0.0.4.dist-info/METADATA
creditkit_tools-0.0.4.dist-info/WHEEL
creditkit_tools-0.0.4.dist-info/top_level.txt
creditkit_tools-0.0.4.dist-info/RECORD
