Metadata-Version: 2.1
Name: creditkit-tools
Version: 0.0.4
Summary: A little bit kit of develop for creditkit project
Home-page: https://github.com/JanoBourian/utils-creditkit
Author: janobourian
Author-email: supermath33@hotmail.com
Project-URL: Bug Tracker, https://github.com/JanoBourian/utils-creditkit/issues
Classifier: Programming Language :: Python :: 3
Classifier: License :: OSI Approved :: MIT License
Classifier: Operating System :: OS Independent
Requires-Python: >=3.6
License-File: LICENSE
